Workbook

Sheet Suppliers
A1: Total | B1: GBP | C1: USD | D1: Retail | H1: USD:GBP | I1: =IFERROR(__xludf.DUMMYFUNCTION("GOOGLEFINANCE(""usd-gbp"")"),0.7528549999999999) -> 0.752855
A2: Gyuto | B2: =Gyutos!I16 -> 1954.788 | D2: =B2/0.6 -> 3257.98
A3: Santoku | B3: =Santokus!I10 -> 986.76705 | D3: =B3/0.6 -> 1644.6117
A4: Cleaver | B4: =Cleaver!I4 -> 133.78233 | D4: =B4/0.6 -> 222.97056
A5: Knife Set | B5: ='Knife Sets'!F5 -> 619.97609 | D5: =B5/0.6 -> 1033.2935
A6: Kirisuke | B6: =Kiritsuke!I8 -> 387.53211 | D6: =B6/0.6 -> 645.88685
A7: Bread Knife | B7: ='Bread Knife'!H4 -> 127.2325 | D7: =B7/0.6 -> 212.05416
A8: Nakiri | B8: =Nakiri!I6 -> 226.45878 | D8: =B8/0.6 -> 377.43131
A9: Butcher Knives | B9: ='Butcher Knife'!I5 -> 48.258006 | D9: =B9/0.6 -> 80.430009
A10: Standard Boxes | B10: =C10*I1 -> 171.27451 | C10: 227.5
A11: Knife Set Boxes | B11: =C11*I1 -> 73.403363 | C11: 97.5
A12: Total | B12: =SUM(B2:B11) -> 4729.4728
A13: Actual | B13: 5217.1
A14: Payment Fees | B14: 156
A15: Shipping | B15: =B13-B12 -> 487.62725 | C15: 0
A16: Duty | B16: 0
A17: Vat | B17: 0
A19: Final Bill | B19: =SUM(B12:B17)-B13 -> 5373.1 | C19: =B19/I1 -> 7136.9653
A20: Total No. Knives | B20: =SUM(Gyutos!H16+Santokus!H10+Cleaver!H4+'Knife Sets'!E5+Kiritsuke!H8+'Bread Knife'!G4+Nakiri!H6+'Butcher Knife'!H5) -> 345
A21: Cost to import per knife | B21: =(SUM(B14:B17)/B20) -> 1.8655862
A22: Av cost per knife | B22: =B12/B20 -> 13.708617
A23: Av Cog | B23: =B22+B21 -> 15.574203

Sheet Gyutos
A1: Image | B1: Inch | C1: SKU | D1: Handle | E1: Material | F1: Price USD | G1: Price GBP | H1: Qty | J1: Import | K1: Packaging | L1: Postage | M1: COG | N1: RRP | O1: GM
B2: 8 | C2: DMS-151A | D2: Ebony +Solidified Wood | E2: Dam | F2: 23.4 | G2: =F2*Suppliers!$I$1 -> 17.616807 | H2: 10 | I2: =H2*G2 -> 176.16807 | J2: =Suppliers!$B$21 -> 1.8655862 | K2: 0.52 | L2: 3.78 | M2: =G2+J2+K2+L2 -> 23.782393 | N2: 59.99 | O2: =(N2-M2)/N2 -> 0.60356071
B3: 7.9 | C3: DMS-148A | D3: Rose wood | E3: Dam | F3: 22.87 | G3: =F3*Suppliers!$I$1 -> 17.217794 | H3: 10 | I3: =H3*G3 -> 172.17794 | J3: =Suppliers!$B$21 -> 1.8655862 | K3: 0.52 | L3: 3.78 | M3: =G3+J3+K3+L3 -> 23.38338 | N3: 59.99 | O3: =(N3-M3)/N3 -> 0.61021203
B4: 8 | C4: DMS-132A | D4: Olive wood | E4: Dam | F4: 23.84 | G4: =F4*Suppliers!$I$1 -> 17.948063 | H4: 10 | I4: =H4*G4 -> 179.48063 | J4: =Suppliers!$B$21 -> 1.8655862 | K4: 0.52 | L4: 3.78 | M4: =G4+J4+K4+L4 -> 24.113649 | N4: 59.99 | O4: =(N4-M4)/N4 -> 0.59803885
B5: 8.5 | C5: DMS-119G | D5: Ebony wood | E5: Dam | F5: 21.23 | G5: =F5*Suppliers!$I$1 -> 15.983112 | H5: 10 | I5: =H5*G5 -> 159.83112 | J5: =Suppliers!$B$21 -> 1.8655862 | K5: 0.52 | L5: 3.78 | M5: =G5+J5+K5+L5 -> 22.148698 | N5: 59.99 | O5: =(N5-M5)/N5 -> 0.6307935
B6: 8 | C6: HM-20A | D6: Hardwood | E6: AUS10 Steel | F6: 19.31 | G6: =F6*Suppliers!$I$1 -> 14.53763 | H6: 10 | I6: =H6*G6 -> 145.3763 | J6: =Suppliers!$B$21 -> 1.8655862 | K6: 0.52 | L6: 3.78 | M6: =G6+J6+K6+L6 -> 20.703216 | N6: 54.99 | O6: =(N6-M6)/N6 -> 0.62350943
B7: 8 | C7: HM-19A | D7: Mkuruti wood | E7: AUS10 Steel | F7: 11.68 | G7: =F7*Suppliers!$I$1 -> 8.7933464 | H7: 10 | I7: =H7*G7 -> 87.933464 | J7: =Suppliers!$B$21 -> 1.8655862 | K7: 0.52 | L7: 3.78 | M7: =G7+J7+K7+L7 -> 14.958933 | N7: 49.99 | O7: =(N7-M7)/N7 -> 0.7007615
B8: 8 | C8: HM-19A1 | D8: Olive wood | E8: AUS10 Steel | F8: 14.09 | G8: =F8*Suppliers!$I$1 -> 10.607727 | H8: 10 | I8: =H8*G8 -> 106.07727 | J8: =Suppliers!$B$21 -> 1.8655862 | K8: 0.52 | L8: 3.78 | M8: =G8+J8+K8+L8 -> 16.773313 | N8: 49.99 | O8: =(N8-M8)/N8 -> 0.66446663
B9: 8 | C9: HM-6A | D9: Mkuruti wood | E9: SS | F9: 7.24 | G9: =F9*Suppliers!$I$1 -> 5.4506702 | H9: 10 | I9: =H9*G9 -> 54.506702 | J9: =Suppliers!$B$21 -> 1.8655862 | K9: 0.52 | L9: 3.78 | M9: =G9+J9+K9+L9 -> 11.616256 | N9: 39.99 | O9: =(N9-M9)/N9 -> 0.70952097
B10: 8.5 | C10: HM-51A | D10: Mkuruti wood | E10: SS | F10: 13.16 | G10: =F10*Suppliers!$I$1 -> 9.9075718 | H10: 10 | I10: =H10*G10 -> 99.075718 | J10: =Suppliers!$B$21 -> 1.8655862 | K10: 0.52 | L10: 3.78 | M10: =G10+J10+K10+L10 -> 16.073158 | N10: 39.99 | O10: =(N10-M10)/N10 -> 0.59807057
B11: 8 | C11: TD-0012A | D11: Pakka wood | E11: SS | F11: 4 | G11: =F11*Suppliers!$I$1 -> 3.01142 | H11: 10 | I11: =H11*G11 -> 30.1142 | J11: =Suppliers!$B$21 -> 1.8655862 | K11: 0.52 | L11: 3.78 | M11: =G11+J11+K11+L11 -> 9.1770062 | N11: 39.99 | O11: =(N11-M11)/N11 -> 0.77051747
B12: 8 | C12: DMS-106T | D12: Carbon fiber | E12: Dam | F12: 23.83 | G12: =F12*Suppliers!$I$1 -> 17.940535 | H12: 10 | I12: =H12*G12 -> 179.40535 | J12: =Suppliers!$B$21 -> 1.8655862 | K12: 0.52 | L12: 3.78 | M12: =G12+J12+K12+L12 -> 24.106121 | N12: 59.99 | O12: =(N12-M12)/N12 -> 0.59816435
B13: 8.3 | C13: DMS-146A | D13: Carbon fiber | E13: Dam | F13: 27.08 | G13: =F13*Suppliers!$I$1 -> 20.387313 | H13: 10 | I13: =H13*G13 -> 203.87313 | J13: =Suppliers!$B$21 -> 1.8655862 | K13: 0.52 | L13: 3.78 | M13: =G13+J13+K13+L13 -> 26.5529 | N13: 64.99 | O13: =(N13-M13)/N13 -> 0.591431
... B15: 8 | C15: DMS-125A | D15: Resin + hardwood | E15: Dam | F15: 23.58 | G15: =F15*Suppliers!$I$1 -> 17.752321 | H15: 10 | I15: =H15*G15 -> 177.52321 | J15: =Suppliers!$B$21 -> 1.8655862 | K15: 0.52 | L15: 3.78 | M15: =G15+J15+K15+L15 -> 23.917907 | N15: 59.99 | O15: =(N15-M15)/N15 -> 0.60130176
G16: Total | H16: =SUM(H2:H15) -> 140 | I16: =SUM(I2:I15) -> 1954.788
A18: Yoshi | B18: 8 | C18: YOSHI-GYT | E18: Dam | F18: =G18/Suppliers!I1 -> 22.76348 | G18: =I18/H18 -> 17.1376 | H18: 50 | I18: 856.88 | J18: 0 | K18: 0 | L18: 3.78 | M18: =G18+J18+K18+L18 -> 20.9176 | N18: 59.99 | O18: =(N18-M18)/N18 -> 0.65131522
B20: 8 | C20: DMS-136A | D20: White resin | E20: Dam | F20: 20.58 | G20: =F20*Suppliers!$I$1 -> 15.493756 | H20: 10 | I20: =H20*G20 -> 154.93756 | J20: =Suppliers!$B$21 -> 1.8655862 | K20: 0.52 | L20: 3.78 | M20: =G20+J20+K20+L20 -> 21.659342
B21: 8 | C21: DMS-122A-GREEN | D21: Resin | E21: Dam | F21: 24.34 | G21: =F21*Suppliers!$I$1 -> 18.324491 | H21: 10 | I21: =H21*G21 -> 183.24491 | J21: =Suppliers!$B$21 -> 1.8655862 | K21: 0.52 | L21: 3.78 | M21: =G21+J21+K21+L21 -> 24.490077
B22: 7.7 | C22: DMS-018A | D22: Pakka | E22: Dam | F22: 21.43 | G22: =F22*Suppliers!$I$1 -> 16.133683 | H22: 10 | I22: =H22*G22 -> 161.33683 | J22: =Suppliers!$B$21 -> 1.8655862 | K22: 0.52 | L22: 3.78 | M22: =G22+J22+K22+L22 -> 22.299269
B23: 8 | C23: DMS-120T-RED | D23: Resin | E23: Dam | F23: 23.58 | G23: =F23*Suppliers!$I$1 -> 17.752321 | H23: 10 | I23: =H23*G23 -> 177.52321 | J23: =Suppliers!$B$21 -> 1.8655862 | K23: 0.52 | L23: 3.78 | M23: =G23+J23+K23+L23 -> 23.917907
B24: 7.5 | C24: DMS-126A | D24: Rose wood | E24: Dam | F24: 21.42 | G24: =F24*Suppliers!$I$1 -> 16.126154 | H24: 10 | I24: =H24*G24 -> 161.26154 | J24: =Suppliers!$B$21 -> 1.8655862 | K24: 0.52 | L24: 3.78 | M24: =G24+J24+K24+L24 -> 22.29174

Sheet Santokus
A1: Image | B1: Inch | C1: SKU | D1: Handle | E1: Material | F1: Price USD | G1: Price GBP | H1: Qty | I1: Price | J1: Import | K1: Packaging | L1: Postage | M1: COG | N1: RRP | O1: GM
B2: 7 | C2: DMS-151B | D2: Ebony +Solidified Wood+Solidified Wood" | E2: Dam | F2: 22.4 | G2: =F2*Suppliers!$I$1 -> 16.863952 | H2: 10 | I2: =G2*H2 -> 168.63952 | J2: =Suppliers!$B$21 -> 1.8655862 | K2: 0.52 | L2: 3.78 | M2: =SUM(G2+J2+K2+L2) -> 23.029538 | N2: 55.99 | O2: =(N2-M2)/N2 -> 0.5886848
B3: 7 | C3: DMS-148B | D3: Rose Wood | E3: Dam | F3: 22.4 | G3: =F3*Suppliers!$I$1 -> 16.863952 | H3: 10 | I3: =G3*H3 -> 168.63952 | J3: =Suppliers!$B$21 -> 1.8655862 | K3: 0.52 | L3: 3.78 | M3: =SUM(G3+J3+K3+L3) -> 23.029538 | N3: 55.99 | O3: =(N3-M3)/N3 -> 0.5886848
B4: 7 | C4: DMS-132B | D4: Olive Wood | E4: Dam | F4: 23.4 | G4: =F4*Suppliers!$I$1 -> 17.616807 | H4: 10 | I4: =G4*H4 -> 176.16807 | J4: =Suppliers!$B$21 -> 1.8655862 | K4: 0.52 | L4: 3.78 | M4: =SUM(G4+J4+K4+L4) -> 23.782393 | N4: 56.99 | O4: =(N4-M4)/N4 -> 0.58269182
B5: 5 | C5: HM-50B | D5: Hard wood | E5: AUS10 Steel | F5: 16.1 | G5: =F5*Suppliers!$I$1 -> 12.120966 | H5: 10 | I5: =G5*H5 -> 121.20965 | J5: =Suppliers!$B$21 -> 1.8655862 | K5: 0.52 | L5: 3.78 | M5: =SUM(G5+J5+K5+L5) -> 18.286552 | N5: 49.99 | O5: =(N5-M5)/N5 -> 0.6341958
B6: 7.5 | C6: HM-19B | D6: Mkuruti wood | E6: AUS10 Steel | F6: 11.68 | G6: =F6*Suppliers!$I$1 -> 8.7933464 | H6: 10 | I6: =G6*H6 -> 87.933464 | J6: =Suppliers!$B$21 -> 1.8655862 | K6: 0.52 | L6: 3.78 | M6: =SUM(G6+J6+K6+L6) -> 14.958933 | N6: 44.99 | O6: =(N6-M6)/N6 -> 0.66750539
B7: 7 | C7: HM-6B | D7: Mkuruti wood | E7: SS | F7: 9.66 | G7: =F7*Suppliers!$I$1 -> 7.2725793 | H7: 10 | I7: =G7*H7 -> 72.725793 | J7: =Suppliers!$B$21 -> 1.8655862 | K7: 0.52 | L7: 3.78 | M7: =SUM(G7+J7+K7+L7) -> 13.438166 | N7: 39.99 | O7: =(N7-M7)/N7 -> 0.66396185
B8: 6.5 | C8: TD-0012B | D8: Pakka wood | E8: SS | F8: 4 | G8: =F8*Suppliers!$I$1 -> 3.01142 | H8: 10 | I8: =G8*H8 -> 30.1142 | J8: =Suppliers!$B$21 -> 1.8655862 | K8: 0.52 | L8: 3.78 | M8: =SUM(G8+J8+K8+L8) -> 9.1770062 | N8: 39.99 | O8: =(N8-M8)/N8 -> 0.77051747
B9: 7 | C9: DMS-018B | D9: Pakka wood | E9: DAM | F9: 21.43 | G9: =F9*Suppliers!$I$1 -> 16.133683 | H9: 10 | I9: =G9*H9 -> 161.33683 | J9: =Suppliers!$B$21 -> 1.8655862 | K9: 0.52 | L9: 3.78 | M9: =SUM(G9+J9+K9+L9) -> 22.299269 | N9: 55.99 | O9: =(N9-M9)/N9 -> 0.60172765
G10: Total | H10: =SUM(H2:H9) -> 80 | I10: =SUM(I2:I9) -> 986.76705
B12: 7 | C12: DMS-138B | D12: White resin | E12: Dam | F12: 20.58
B13: 7 | C13: DMS-126B | D13: Rose wood | E13: Dam | F13: 21.42
B14: 7 | C14: DMS-131B | D14: Resin + Abalone | E14: Dam | F14: 19.72
B15: 7 | C15: DMS-103B | D15: Sandal wood | E15: Dam | F15: 22.99
B16: 7 | C16: DMS-134B | D16: Carbon fiber & golden foil | E16: Dam | F16: 23.4

Sheet Cleaver
A1: Image | B1: Inch | C1: SKU | D1: Supplier | E1: Material | F1: Price USD | G1: Price GBP | H1: Qty | I1: Price | J1: Import | K1: Packaging | L1: Postage | M1: COG | N1: RRP | O1: GM
B2: 7 | E2: SS | F2: 7.8 | G2: =F2*Suppliers!$I$1 -> 5.872269 | H2: 10 | I2: =G2*H2 -> 58.72269 | J2: =Suppliers!$B$21 -> 1.8655862 | K2: 0.52 | L2: 3.78 | M2: =SUM(G2+J2+K2+L2) -> 12.037855 | N2: 34.99 | O2: =(N2-M2)/N2 -> 0.65596298
B3: 7 | E3: SS | F3: 9.97 | G3: =F3*Suppliers!$I$1 -> 7.5059644 | H3: 10 | I3: =G3*H3 -> 75.059644 | J3: =Suppliers!$B$21 -> 1.8655862 | K3: 0.52 | L3: 3.78 | M3: =SUM(G3+J3+K3+L3) -> 13.671551 | N3: 34.99 | O3: =(N3-M3)/N3 -> 0.60927263
G4: Total | H4: =SUM(H2:H3) -> 20 | I4: =SUM(I2:I3) -> 133.78233

Sheet Knife Sets
A1: Image | B1: SKU | C1: Price USD | D1: Price GBP | E1: QTY | F1: Total | G1: Import | H1: Packaging | I1: Postage | J1: COG | K1: RRP | L1: GM
B2: TD-006 | C2: 28.63 | D2: =C2*Suppliers!$I$1 -> 21.554239 | E2: 10 | F2: =E2*D2 -> 215.54239 | G2: =Suppliers!$B$21 -> 1.8655862 | H2: 2.4 | I2: 3.78 | J2: =SUM(D2+G2+H2+I2) -> 29.599825 | K2: 139.99 | L2: =(K2-J2)/K2 -> 0.78855758
B3: TD-007 | C3: 28.63 | D3: =C3*Suppliers!$I$1 -> 21.554239 | E3: 10 | F3: =E3*D3 -> 215.54239 | G3: =Suppliers!$B$21 -> 1.8655862 | H3: 2.4 | I3: 3.78 | J3: =SUM(D3+G3+H3+I3) -> 29.599825 | K3: 139.99 | L3: =(K3-J3)/K3 -> 0.78855758
B4: TD-002 | C4: 25.09 | D4: =C4*Suppliers!$I$1 -> 18.889132 | E4: 10 | F4: =E4*D4 -> 188.89132 | G4: =Suppliers!$B$21 -> 1.8655862 | H4: 2.4 | I4: 3.78 | J4: =SUM(D4+G4+H4+I4) -> 26.934718 | K4: 134.99 | L4: =(K4-J4)/K4 -> 0.80046879
D5: Total | E5: =SUM(E2:E4) -> 30 | F5: =SUM(F2:F4) -> 619.97609
A7: These are for the 8 knives sets

Sheet Kiritsuke
A1: Image | B1: Inch | C1: SKU | D1: Supplier | E1: Material | F1: Price USD | G1: Price GBP | H1: Qty | I1: Price | J1: Import | K1: Packaging | L1: Postage | M1: COG | N1: RRP | O1: GM
B2: 9.5 | C2: DMS-151K | D2: GS | E2: Dam | F2: 23.4 | G2: =F2*Suppliers!$I$1 -> 17.616807 | H2: 5 | I2: =G2*H2 -> 88.084035 | J2: =Suppliers!$B$21 -> 1.8655862 | K2: 0.52 | L2: 3.78 | M2: =SUM(G2+J2+K2+L2) -> 23.782393 | N2: 69.99 | O2: =(N2-M2)/N2 -> 0.66020298
C3: DMS-148K | D3: GS | E3: Dam | F3: 23.33 | G3: =F3*Suppliers!$I$1 -> 17.564107 | H3: 5 | I3: =G3*H3 -> 87.820536 | J3: =Suppliers!$B$21 -> 1.8655862 | K3: 0.52 | L3: 3.78 | M3: =SUM(G3+J3+K3+L3) -> 23.729693 | N3: 69.99 | O3: =(N3-M3)/N3 -> 0.66095595
B4: 8.2 | C4: DMS-119A | E4: Dam | F4: 21.23 | G4: =F4*Suppliers!$I$1 -> 15.983112 | H4: 5 | I4: =G4*H4 -> 79.915558 | J4: =Suppliers!$B$21 -> 1.8655862 | K4: 0.52 | L4: 3.78 | M4: =SUM(G4+J4+K4+L4) -> 22.148698 | N4: 65.99 | O4: =(N4-M4)/N4 -> 0.66436281
B5: 8.5 | C5: HM-19K | E5: AUS10 Steel | F5: 12.58 | G5: =F5*Suppliers!$I$1 -> 9.4709159 | H5: 5 | I5: =G5*H5 -> 47.354579 | J5: =Suppliers!$B$21 -> 1.8655862 | K5: 0.52 | L5: 3.78 | M5: =SUM(G5+J5+K5+L5) -> 15.636502 | N5: 59.99 | O5: =(N5-M5)/N5 -> 0.73934819
B6: 7 | C6: HM-19K1 | E6: AUS10 Steel | F6: 15.17 | G6: =F6*Suppliers!$I$1 -> 11.42081 | H6: 5 | I6: =G6*H6 -> 57.104052 | J6: =Suppliers!$B$21 -> 1.8655862 | K6: 0.52 | L6: 3.78 | M6: =SUM(G6+J6+K6+L6) -> 17.586397 | N6: 55.99 | O6: =(N6-M6)/N6 -> 0.68590111
B7: 8.5 | C7: HM-6K | E7: SS | F7: 7.24 | G7: =F7*Suppliers!$I$1 -> 5.4506702 | H7: 5 | I7: =G7*H7 -> 27.253351 | J7: =Suppliers!$B$21 -> 1.8655862 | K7: 0.52 | L7: 3.78 | M7: =SUM(G7+J7+K7+L7) -> 11.616256 | N7: 45.99 | O7: =(N7-M7)/N7 -> 0.74741778
G8: Total | H8: =SUM(H2:H7) -> 30 | I8: =SUM(I2:I7) -> 387.53211

Sheet Bread Knife
A1: Image | B1: SKU | C1: Supplier | D1: Material | E1: Price USD | F1: Price GBP | G1: Qty | H1: Price | I1: Import | J1: Packaging | K1: Postage | L1: COG | M1: RRP | N1: GM
B2: HM-19H | C2: GS | D2: AUS10 Steel | E2: 14.3 | F2: =E2*Suppliers!$I$1 -> 10.765826 | G2: 5 | H2: =G2*F2 -> 53.829133 | I2: =Suppliers!$B$21 -> 1.8655862 | J2: 0.52 | K2: 3.78 | L2: =SUM(F2+I2+J2+K2) -> 16.931413 | M2: 49.99 | N2: =(M2-L2)/M2 -> 0.66130401
B3: DMS-136H | C3: GS | D3: Dam | E3: 19.5 | F3: =E3*Suppliers!$I$1 -> 14.680673 | G3: 5 | H3: =G3*F3 -> 73.403363 | I3: =Suppliers!$B$21 -> 1.8655862 | J3: 0.52 | K3: 3.78 | L3: =SUM(F3+I3+J3+K3) -> 20.846259 | M3: 59.99 | N3: =(M3-L3)/M3 -> 0.65250444
F4: Total | G4: =SUM(G2:G3) -> 10 | H4: =SUM(H2:H3) -> 127.2325
B8: HM-19H | C8: GS | D8: AUS10 Steel | E8: 14.3 | F8: =E8*Suppliers!$I$1 -> 10.765826 | G8: 5 | H8: =G8*F8 -> 53.829133 | I8: =Suppliers!$B$21 -> 1.8655862 | J8: 0.1 | K8: 5.4 | L8: =SUM(F8+I8+J8+K8) -> 18.131413 | M8: 50.99 | N8: =(M8-L8)/M8 -> 0.64441238

Sheet Nakiri
A1: Image | C1: SKU | D1: Supplier | E1: Material | F1: Price USD | G1: Price GBP | H1: Qty | J1: Import | K1: Packaging | L1: Postage | M1: COG | N1: RRP | O1: GM
B2: 7 | C2: DMS-119C | D2: GS | E2: Dam | F2: 21.23 | G2: =F2*Suppliers!$I$1 -> 15.983112 | H2: 5 | I2: =H2*G2 -> 79.915558 | J2: =Suppliers!$B$21 -> 1.8655862 | K2: 0.52 | L2: 3.78 | M2: =SUM(G2+J2+K2+L2) -> 22.148698 | N2: 59.99 | O2: =(N2-M2)/N2 -> 0.6307935
B3: 7 | C3: HM-19C | E3: AUS10 Steel | F3: 11.68 | G3: =F3*Suppliers!$I$1 -> 8.7933464 | H3: 5 | I3: =H3*G3 -> 43.966732 | J3: =Suppliers!$B$21 -> 1.8655862 | K3: 0.52 | L3: 3.78 | M3: =SUM(G3+J3+K3+L3) -> 14.958933 | N3: 49.99 | O3: =(N3-M3)/N3 -> 0.7007615
B4: 7 | C4: HM-19C1 | E4: AUS10 Steel | F4: 14.09 | G4: =F4*Suppliers!$I$1 -> 10.607727 | H4: 5 | I4: =H4*G4 -> 53.038635 | J4: =Suppliers!$B$21 -> 1.8655862 | K4: 0.52 | L4: 3.78 | M4: =SUM(G4+J4+K4+L4) -> 16.773313 | N4: 49.99 | O4: =(N4-M4)/N4 -> 0.66446663
B5: 7.5 | C5: HM-51C | E5: SS | F5: 13.16 | G5: =F5*Suppliers!$I$1 -> 9.9075718 | H5: 5 | I5: =H5*G5 -> 49.537859 | J5: =Suppliers!$B$21 -> 1.8655862 | K5: 0.52 | L5: 3.78 | M5: =SUM(G5+J5+K5+L5) -> 16.073158 | N5: 45.99 | O5: =(N5-M5)/N5 -> 0.65050754
G6: Total | H6: =SUM(H2:H5) -> 20 | I6: =SUM(I2:I5) -> 226.45878

Sheet Butcher Knife
A1: Image | B1: Inch | C1: SKU | D1: Supplier | E1: Material | F1: Price USD | G1: Price GBP | H1: Qty | J1: Import | K1: Packaging | L1: Postage | M1: COG | N1: RRP | O1: GM
B2: 5.8 | C2: HM-24 | D2: GS | E2: SS | F2: 4.59 | G2: =F2*Suppliers!$I$1 -> 3.4556045 | H2: 5 | I2: =H2*G2 -> 17.278022 | J2: =Suppliers!$B$21 -> 1.8655862 | K2: 0.52 | L2: 3.78 | M2: =SUM(G2+J2+K2+L2) -> 9.6211907 | N2: 34.99 | O2: =(N2-M2)/N2 -> 0.72503028
B3: 5.2 | C3: HM-49 | D3: GS | E3: SS | F3: 4.12 | G3: =F3*Suppliers!$I$1 -> 3.1017626 | H3: 5 | I3: =H3*G3 -> 15.508813 | J3: =Suppliers!$B$21 -> 1.8655862 | K3: 0.52 | L3: 3.78 | M3: =SUM(G3+J3+K3+L3) -> 9.2673488 | N3: 34.99 | O3: =(N3-M3)/N3 -> 0.73514293
B4: 5.7 | C4: FIB-30-BROWN | D4: GS | E4: SS | F4: 4.11 | G4: =F4*Suppliers!$I$1 -> 3.094234 | H4: 5 | I4: =H4*G4 -> 15.47117 | J4: =Suppliers!$B$21 -> 1.8655862 | K4: 0.52 | L4: 3.78 | M4: =SUM(G4+J4+K4+L4) -> 9.2598203 | N4: 34.99 | O4: =(N4-M4)/N4 -> 0.73535809
G5: Total | H5: =SUM(H2:H4) -> 15 | I5: =SUM(I2:I4) -> 48.258006

Sheet Steak
A1: Image | B1: Inch | C1: SKU | D1: Handle | E1: Material | F1: Price USD | G1: Price GBP | H1: Qty | J1: Import | K1: Packaging | L1: Postage | M1: COG | N1: RRP | O1: GM
C2: DMS-008S-4pcs | D2: Black g10 | E2: dam | F2: 36.76
